[
    {
        "id": 475779,
        "config": "labels_all"
    },
    {
        "id": 301867,
        "config": "labels_all"
    },
    {
        "id": 312421,
        "config": "no_image"
    },
    {
        "id": 185250,
        "config": "clear_all"
    },
    {
        "id": 356427,
        "config": "labels_crop"
    },
    {
        "id": 572517,
        "config": "labels_crop"
    },
    {
        "id": 270244,
        "config": "labels_text"
    },
    {
        "id": 125211,
        "config": "no_image"
    },
    {
        "id": 562121,
        "config": "clear_all"
    },
    {
        "id": 16228,
        "config": "labels_crop"
    },
    {
        "id": 266409,
        "config": "labels_text"
    },
    {
        "id": 476258,
        "config": "no_image"
    },
    {
        "id": 349860,
        "config": "labels_text"
    },
    {
        "id": 486438,
        "config": "original"
    },
    {
        "id": 502737,
        "config": "labels_crop"
    },
    {
        "id": 355257,
        "config": "no_image"
    }
]